hydra_plugins/zendag_config_search_path.py
zendag/__init__.py
zendag/config_utils.py
zendag/core.py
zendag/mlflow_utils.py
zendag/run.py
zendag/start_pipeline.py
zendag_hydra_conf/__init__.py
zendag_hydra_conf/hydra/callbacks/basic_logging.yaml
zendag_hydra_conf/hydra/callbacks/link_projroot.yaml
zendag_hydra_conf/zendag/base.yaml
zendag-0.1.5.dist-info/METADATA
zendag-0.1.5.dist-info/WHEEL
zendag-0.1.5.dist-info/licenses/LICENSE
zendag-0.1.5.dist-info/RECORD
