Metadata-Version: 2.4
Name: zendag
Version: 0.1.5
Summary: A framework for integrating Hydra/DVC/MLflow for reproducible ML experiments.
Project-URL: Homepage, https://github.com/quentinf00/zendag
Project-URL: Repository, https://github.com/quentinf00/zendag
Project-URL: Issues, https://github.com/quentinf00/zendag/issues
Project-URL: Documentation, https://quentinf00.github.io/zendag
Author-email: Your Name <your.email@example.com>
License: 
License-File: LICENSE
Keywords: dvc,hydra,machine-learning,mlflow,mlops,reproducibility,workflow
Classifier: Development Status :: 3 - Alpha
Classifier: Intended Audience :: Developers
Classifier: Intended Audience :: Science/Research
Classifier: License :: OSI Approved :: MIT License
Classifier: Operating System :: OS Independent
Classifier: Programming Language :: Python :: 3
Classifier: Programming Language :: Python :: 3.9
Classifier: Programming Language :: Python :: 3.10
Classifier: Programming Language :: Python :: 3.11
Classifier: Topic :: Scientific/Engineering :: Artificial Intelligence
Classifier: Topic :: Software Development :: Libraries :: Python Modules
Classifier: Topic :: Utilities
Requires-Python: >=3.9
Requires-Dist: hydra-zen<1.0,>=0.14.0
Requires-Dist: mlflow<4.0,>=2.0.0
Requires-Dist: pandas<3.0,>=1.3.0
Requires-Dist: toolz<1.0,>=0.11.0
Provides-Extra: dev
Requires-Dist: mypy>=1.0; extra == 'dev'
Requires-Dist: pre-commit>=3.0; extra == 'dev'
Requires-Dist: pytest-cov>=3.0; extra == 'dev'
Requires-Dist: pytest>=7.0; extra == 'dev'
Requires-Dist: ruff>=0.1.0; extra == 'dev'
Provides-Extra: docs
Requires-Dist: ipykernel; extra == 'docs'
Requires-Dist: jupyter-client; extra == 'docs'
Requires-Dist: myst-nb<1.1,>=0.17; extra == 'docs'
Requires-Dist: sphinx-autodoc-typehints<2.0,>=1.20; extra == 'docs'
Requires-Dist: sphinx-copybutton<0.6,>=0.5; extra == 'docs'
Requires-Dist: sphinx-rtd-theme<2.0,>=1.0; extra == 'docs'
Requires-Dist: sphinx<8.0,>=5.0; extra == 'docs'
